{
  "routes": [
    {
      "method": "GET",
      "path": "/contestors",
      "handler": "contestor.find",
      "config": {
        "policies": []
      }
    },
    {
      "method": "GET",
      "path": "/contestors/count",
      "handler": "contestor.count",
      "config": {
        "policies": []
      }
    },
    {
      "method": "GET",
      "path": "/contestors/:id",
      "handler": "contestor.findOne",
      "config": {
        "policies": []
      }
    },
    {
      "method": "POST",
      "path": "/contestors",
      "handler": "contestor.create",
      "config": {
        "policies": []
      }
    },
    {
      "method": "PUT",
      "path": "/contestors/:id",
      "handler": "contestor.update",
      "config": {
        "policies": []
      }
    },
    {
      "method": "DELETE",
      "path": "/contestors/:id",
      "handler": "contestor.delete",
      "config": {
        "policies": []
      }
    }
  ]
}
